{
    "name": "210",
    "description": "Set GPRS Alarm Event",
    "indexField": "index",
    "indexRange": [1, 2],
    "indexValue": [1, 2, 4, 8, 16, 32, 64, 128],
    "bitwise": false,
    "usePassword": false,
    "useTag": false,
    "fields": [
      {
        "name": "index",
        "label": "index",
        "type": "index",
        "data": [],
        "description": "server number, 1 is the GPRS event of server 1, and 2 is the GPRS event of server 2"
      },
      {
        "name": "operation",
        "label": "operation",
        "type": "select",
        "value": 1,
        "data": [[1, "setting"], [2, "adding"], [3, "deleting"]],
        "description": "operation code, 1 is setting, 2 is adding, 3 is deleting"
      },
      {
        "name": "code:",
        "label": "code:",
        "type": "textList",
        "description": "event code table, each event is separated by‘,’;"
      }
    ]
  }
  